analyser2_hj3415/__init__.py
analyser2_hj3415/cli/__init__.py
analyser2_hj3415/cli/fscore.py
analyser2_hj3415/cli/tsseer.py
analyser2_hj3415/fscore/__init__.py
analyser2_hj3415/fscore/blue.py
analyser2_hj3415/fscore/growth.py
analyser2_hj3415/fscore/mil.py
analyser2_hj3415/fscore/red.py
analyser2_hj3415/fscore/utils/__init__.py
analyser2_hj3415/fscore/utils/financial.py
analyser2_hj3415/fscore/utils/math_utils.py
analyser2_hj3415/fscore/utils/mongo_utils.py
analyser2_hj3415/tsa/__init__.py
analyser2_hj3415/tsa/common.py
analyser2_hj3415/tsa/lstm.py
analyser2_hj3415/tsa/myprophet.py
analyser2_hj3415/tsseer/__init__.py
analyser2_hj3415/tsseer/mydarts.py
analyser2_hj3415/tsseer/myprophet.py
analyser2_hj3415/tsseer/utils.py
analyser2_hj3415/tsseer/models/__init__.py
analyser2_hj3415/tsseer/models/nbeats.py
analyser2_hj3415/tsseer/models/nhits.py
analyser2_hj3415/tsseer/models/prophet.py
analyser2_hj3415/tsseer/models/utils.py
analyser2_hj3415-0.6.2.dist-info/entry_points.txt
analyser2_hj3415-0.6.2.dist-info/WHEEL
analyser2_hj3415-0.6.2.dist-info/METADATA
analyser2_hj3415-0.6.2.dist-info/RECORD
