Metadata-Version: 2.4
Name: analyser2_hj3415
Version: 0.6.2
Summary: Analysing the stock data
Author-email: Hyungjin Kim <hj3415@gmail.com>
Classifier: License :: OSI Approved :: MIT License
Requires-Dist: db2-hj3415>=0.4.1
Requires-Dist: redis-hj3415>=0.2.3
Requires-Dist: utils-hj3415>=3.2.6
Requires-Dist: u8darts[all]
Requires-Dist: yfinance
Requires-Dist: matplotlib
Requires-Dist: pandas
Requires-Dist: numpy
Project-URL: Home, https://www.hyungjin.kr
